lescan/__init__.py
lescan/__main__.py
lescan-0.3.0.dist-info/LICENSE
lescan-0.3.0.dist-info/METADATA
lescan-0.3.0.dist-info/WHEEL
lescan-0.3.0.dist-info/entry_points.txt
lescan-0.3.0.dist-info/top_level.txt
lescan-0.3.0.dist-info/RECORD
